splunk_app_packager/__init__.py
splunk_app_packager/acs.py
splunk_app_packager/jinja_replace_dict.py
splunk_app_packager/package.py
splunk_app_packager-0.0.6.dist-info/METADATA
splunk_app_packager-0.0.6.dist-info/WHEEL
splunk_app_packager-0.0.6.dist-info/entry_points.txt
splunk_app_packager-0.0.6.dist-info/licenses/LICENCE
splunk_app_packager-0.0.6.dist-info/RECORD
