Metadata-Version: 2.4
Name: splunk_app_packager
Version: 0.0.6
Summary: A tool to package up your splunk app and deploy it.
Project-URL: Homepage, https://github.com/dfe-digital/splunk-app-packager
Project-URL: Issues, https://github.com/dfe-digital/splunk-app-packager/issues
Author-email: Sam Pritchard <47423802+pritchyspritch@users.noreply.github.com>, Ian Pearl <ian.pearl@education.gov.uk>, Alex Kinnane <17098249+akinnane@users.noreply.github.com>
License-File: LICENCE
Classifier: License :: OSI Approved :: MIT License
Classifier: Operating System :: OS Independent
Classifier: Programming Language :: Python :: 3
Requires-Python: >=3.8
Requires-Dist: click
Requires-Dist: gitpython
Requires-Dist: jinja2
Requires-Dist: requests
Requires-Dist: toml
